[
  {
    "id": "p79",
    "section": "section-08-adjectives",
    "cantonese": "hou2",
    "english": "Good"
  },
  {
    "id": "p80",
    "section": "section-08-adjectives",
    "cantonese": "waai6",
    "english": "Bad"
  },
  {
    "id": "p81",
    "section": "section-08-adjectives",
    "cantonese": "daai6",
    "english": "Big"
  },
  {
    "id": "p82",
    "section": "section-08-adjectives",
    "cantonese": "sai3",
    "english": "Small"
  },
  {
    "id": "p83",
    "section": "section-08-adjectives",
    "cantonese": "leng3",
    "english": "Beautiful / Pretty"
  },
  {
    "id": "p84",
    "section": "section-08-adjectives",
    "cantonese": "caau4",
    "english": "Ugly / Stinky (colloquial)"
  },
  {
    "id": "p85",
    "section": "section-08-adjectives",
    "cantonese": "jam4",
    "english": "Hot (weather/food)"
  },
  {
    "id": "p86",
    "section": "section-08-adjectives",
    "cantonese": "laang5",
    "english": "Cold"
  },
  {
    "id": "p87",
    "section": "section-08-adjectives",
    "cantonese": "hoeng1",
    "english": "Fragrant"
  },
  {
    "id": "p88",
    "section": "section-08-adjectives",
    "cantonese": "naam4 / taan2",
    "english": "Difficult / Easy"
  },
  {
    "id": "p89",
    "section": "section-08-adjectives",
    "cantonese": "gwai3",
    "english": "Expensive"
  },
  {
    "id": "p90",
    "section": "section-08-adjectives",
    "cantonese": "peng4",
    "english": "Cheap"
  },
  {
    "id": "p91",
    "section": "section-08-adjectives",
    "cantonese": "sun1",
    "english": "New"
  },
  {
    "id": "p92",
    "section": "section-08-adjectives",
    "cantonese": "gau6",
    "english": "Old (things)"
  }
]